pytrends/__init__.py
pytrends/dailydata.py
pytrends/exceptions.py
pytrends/request.py
pytrends/test_trendReq.py
pytrends_dqna-1.0.0.dist-info/LICENSE
pytrends_dqna-1.0.0.dist-info/METADATA
pytrends_dqna-1.0.0.dist-info/WHEEL
pytrends_dqna-1.0.0.dist-info/top_level.txt
pytrends_dqna-1.0.0.dist-info/RECORD
