Metadata-Version: 2.1
Name: pytrends-dqna
Version: 1.0.0
Summary: Pseudo API for Google Trends
Home-page: https://github.com/baspenny/pytrends
Author: ['John Hogue', 'Burton DeWilde', 'Sebastiaan Pfennigwerth']
Author-email: spfennigwerth@outlook.com
License: Apache 2.0
Keywords: google trends api search
Platform: UNKNOWN
Classifier: Development Status :: 4 - Beta
Classifier: Intended Audience :: Developers
Classifier: Programming Language :: Python :: 3.3
Classifier: Programming Language :: Python :: 3.4
Classifier: Programming Language :: Python :: 3.5
Classifier: Programming Language :: Python :: 3.6
Classifier: Programming Language :: Python :: 3.7
Classifier: License :: OSI Approved :: MIT License
Requires-Dist: requests (>=2.0)
Requires-Dist: pandas (>=0.25)
Requires-Dist: lxml
